ecovent/__init__.py
ecoventv2/__init__.py
pyEcoventV2-0.9.1.dist-info/LICENSE
pyEcoventV2-0.9.1.dist-info/METADATA
pyEcoventV2-0.9.1.dist-info/WHEEL
pyEcoventV2-0.9.1.dist-info/top_level.txt
pyEcoventV2-0.9.1.dist-info/RECORD
