Metadata-Version: 2.1
Name: pyEcoventV2
Version: 0.9.1
Summary: Python3 library for single-room energy recovery ventilators with api V2 from Vents / Blauberg / Flexit
Home-page: https://github.com/gody01/pyEcoventV2
Author: Matjaž Godec/Aleksander Lehmann
Author-email: matjaz.godec@gmail.com,aleksander@flovik.no
License: MIT
Platform: UNKNOWN
Classifier: Intended Audience :: Developers
Classifier: Operating System :: OS Independent
Classifier: Programming Language :: Python
Classifier: Programming Language :: Python :: 3
Classifier: Topic :: Home Automation
Classifier: Topic :: Software Development :: Libraries :: Python Modules
Requires-Python: >=3.6.7
License-File: LICENSE
